stakenix/__init__.py
stakenix/config.py
stakenix/core/__init__.py
stakenix/core/connectors.py
stakenix/core/databases.py
stakenix/utils/__init__.py
stakenix/utils/common.py
stakenix/utils/generate_config.py
stakenix/utils/generate_env_config.py
stakenix/utils/helpers.py
stakenix-0.2.7.dist-info/WHEEL
stakenix-0.2.7.dist-info/METADATA
stakenix-0.2.7.dist-info/RECORD
